{"back_index.md":"CGpMEG3v","front_javascript_index.md":"AuXlql8w","front_javascript_javascript-interview.md":"DRX68oSC","front_large-screen_index.md":"CjRkqGUN","front_react_index.md":"nCDhguXI","front_react_原理.md":"BMKWZDlT","front_react_提纲.md":"BBCEcgKn","front_react_进阶.md":"Dm8683T8","front_tools_index.md":"CAAEiDWp","front_uniapp_index.md":"CHJMwYap","front_uniapp_常用组件.md":"DdopTmLW","front_vite_index.md":"DVZ9QNdA","front_vue_index.md":"DRVQ7Qda","front_vue_javascript-interview.md":"DRc3y5OD","front_vue_原理篇.md":"CSJbyN7e","front_vue_实践.md":"CVFZv-Kx","front_vue_工程化面试题.md":"DFG1v3zD","front_vue_常见模式.md":"DX8zsQuh","front_vue_面试.md":"BmhpghZU","front_wxapp_index.md":"BpBUsyid","front_wxapp_基础.md":"Dnd6Xp0g","front_wxapp_实践.md":"B2LIsZ1T","front_wxapp_小程序常用开放能力.md":"B00op1q9","front_wxapp_架构.md":"D56aptcE","front_wxapp_配置.md":"DAcym-mw","index.md":"oqmweuiR","myinfo_index.md":"BI-vlGhx","myinfo_instructions.md":"DPuTUQ8C","network_index.md":"rLg8L8Xc","network_面试题.md":"Bd2Dv4N1","operations_git.md":"ZOJLWIh4","tool_index.md":"BsSFZxOo"}
